newsoverview/__init__.py
newsoverview/covid_news.py
newsoverview/en_world_news.py
newsoverview/hospital_news.py
newsoverview/keywords_en.py
newsoverview/protests.py
newsoverview/simple_search.py
newsoverview/terror_monitor.py
newsoverview/tr_world_news.py
newsoverview/travel.py
newsoverview-0.1.3.dist-info/LICENSE
newsoverview-0.1.3.dist-info/METADATA
newsoverview-0.1.3.dist-info/WHEEL
newsoverview-0.1.3.dist-info/top_level.txt
newsoverview-0.1.3.dist-info/RECORD
