Metadata-Version: 2.1
Name: newsoverview
Version: 0.1.3
Summary: News at a glance
Home-page: https://github.com/bethcha/newsoverview
Author: Bethan
Author-email: 89695634+bethcha@users.noreply.github.com
License: MIT
Platform: UNKNOWN
License-File: LICENSE
Requires-Dist: pygooglenews
Requires-Dist: deep-translator
